{
	"animations": [
		{
			"offsets": [
				-50,
				-80
			],
			"indices": [],
			"fps": 24,
			"anim": "idle",
			"loop": false,
			"name": "IDLE"
		},
		{
			"offsets": [
				2,
				-93
			],
			"indices": [],
			"fps": 24,
			"anim": "singLEFT",
			"loop": false,
			"name": "LEFT"
		},
		{
			"offsets": [
				-53,
				-92
			],
			"indices": [],
			"fps": 24,
			"anim": "singDOWN",
			"loop": false,
			"name": "DOWN"
		},
		{
			"offsets": [
				-80,
				-84
			],
			"indices": [],
			"fps": 24,
			"anim": "singUP",
			"loop": false,
			"name": "UP"
		},
		{
			"offsets": [
				-18,
				-71
			],
			"indices": [],
			"fps": 24,
			"anim": "singRIGHT",
			"loop": false,
			"name": "RIGHT"
		}
	],
	"no_antialiasing": false,
	"image": "characters/Dave_Furiosity",
	"position": [
		0,
		0
	],
	"healthicon": "dave3d",
	"flip_x": false,
	"healthbar_colors": [
		255,
		160,
		240
	],
	"camera_position": [
		0,
		110
	],
	"sing_duration": 6.1,
	"scale": 1
}